encore/__init__.py
encore/utils.py
encore/templatetags/__init__.py
encore/templatetags/encore.py
django_encore-0.0.2.dist-info/LICENSE
django_encore-0.0.2.dist-info/METADATA
django_encore-0.0.2.dist-info/WHEEL
django_encore-0.0.2.dist-info/top_level.txt
django_encore-0.0.2.dist-info/RECORD
