Metadata-Version: 2.1
Name: django-encore
Version: 0.0.2
Summary: Django integration with Webpack Encore
Home-page: https://github.com/egorsmkv/django-encore
Author: Yehor Smoliakov
Author-email: yehors@ukr.net
License: MIT
Project-URL: Source, https://github.com/egorsmkv/django-encore
Project-URL: Tracker, https://github.com/egorsmkv/django-encore/issues
Keywords: django django-encore webpack-encore
Platform: UNKNOWN
Classifier: Intended Audience :: Developers
Classifier: Programming Language :: Python
Classifier: Programming Language :: Python :: 3
Classifier: License :: OSI Approved :: MIT License
Classifier: Operating System :: OS Independent
Classifier: Topic :: Software Development :: Libraries :: Python Modules
Classifier: Topic :: Software Development :: Libraries
Classifier: Topic :: Utilities
Classifier: Environment :: Web Environment
Classifier: Framework :: Django
Requires-Python: >=3
Requires-Dist: Django (>=2.2.18)
